pack/__init__.py
sharuijin-1.0.dist-info/LICENSE
sharuijin-1.0.dist-info/METADATA
sharuijin-1.0.dist-info/WHEEL
sharuijin-1.0.dist-info/top_level.txt
sharuijin-1.0.dist-info/RECORD
