Metadata-Version: 2.1
Name: sharuijin
Version: 1.0
Summary: chisini
Home-page: https://github.com/sharuijin/config
Author: test
Author-email: test@qq.com
License: UNKNOWN
Platform: UNKNOWN
